mbtr/__init__.py
mbtr/_splash.py
mbtr/losses.py
mbtr/mbtr.py
mbtr/utils.py
mbtr-0.1.3.dist-info/LICENSE
mbtr-0.1.3.dist-info/METADATA
mbtr-0.1.3.dist-info/WHEEL
mbtr-0.1.3.dist-info/top_level.txt
mbtr-0.1.3.dist-info/RECORD
