Metadata-Version: 2.1
Name: mbtr
Version: 0.1.3
Summary: Multivariate Boosted Trees Regressor package
Home-page: https://github.com/supsi-dacd-isaac/mbtr
Author: Lorenzo Nespoli
Author-email: lorenzo.nespoli@supsi.ch
Classifier: Programming Language :: Python :: 3
Classifier: License :: OSI Approved :: MIT License
Classifier: Operating System :: OS Independent
Requires-Python: >=3.7
License-File: LICENSE
Requires-Dist: matplotlib (>=3.1.2)
Requires-Dist: numpy (>=1.18.1)
Requires-Dist: networkx (>=2.4)
Requires-Dist: tqdm (>=4.41.1)
Requires-Dist: numba (>=0.47.0)
Requires-Dist: scipy (>=1.4.1)
Requires-Dist: twisted (>=20.3.0)
Requires-Dist: requests (>=2.22.0)
Requires-Dist: lightgbm (>=2.3.1)
Requires-Dist: pandas (>=1.0.3)
Requires-Dist: seaborn (>=0.10.1)
